<?xml version="1.0" encoding="UTF-8"?>



<!-- Stripe 
<StateMachine>
	<State name="PaymentForm"
		action="org.paymentserviceframework.stripe.StripeFillOutFormAction"
		nextState="SendTransaction" />
	<State name="SendTransaction"
		action="org.paymentserviceframework.stripe.StripeSendTransactionAction"
		nextState="Finish" />
</StateMachine> 	
-->

<!-- Spreedly  
<StateMachine>
	<State name="PaymentForm"
		action="org.paymentserviceframework.spreedly.SpreedlyFillOutFormAction"
		nextState="SendTransaction"/>
	<State name="SendTransaction"
		action="org.paymentserviceframework.spreedly.SpreedlySendTransactionAction"
		nextState="Finish" /> 		
</StateMachine> -->

<!-- Viva 
<StateMachine>
	<State name="PaymentForm"
		action="org.paymentserviceframework.viva.VivaSendTransactionAction"
		nextState="WaitingForOutcome" />
</StateMachine> -->

<!-- Braintree -->
<StateMachine>
	<State name="PaymentForm"
		action="org.paymentserviceframework.braintree.BraintreeFillOutFormAction"
		nextState="SendTransaction"/>
	<State name="SendTransaction"
		action="org.paymentserviceframework.braintree.BraintreeSendTransactionAction"
		nextState="Finish" /> 		
</StateMachine> 